process_plot/__init__.py
process_plot/api.py
process_plot/cli.py
process_plot/py.typed
process_plot-0.5.2.dist-info/entry_points.txt
process_plot-0.5.2.dist-info/LICENSE
process_plot-0.5.2.dist-info/WHEEL
process_plot-0.5.2.dist-info/METADATA
process_plot-0.5.2.dist-info/RECORD
