Metadata-Version: 2.1
Name: process_plot
Version: 0.5.2
Summary: Create plots of memory usage for a process.
Keywords: memory,profiling
Author: Chris Sewell
Requires-Python: >=3.9
Classifier: License :: OSI Approved :: MIT License
Classifier: Programming Language :: Python :: 3
Classifier: Programming Language :: Python :: 3 :: Only
Classifier: Programming Language :: Python :: Implementation :: CPython
Requires-Dist: typer~=0.12.0
Requires-Dist: matplotlib~=3.4
Requires-Dist: pandas~=2.2
Requires-Dist: psutil~=5.8
Requires-Dist: typing-extensions; python_version < '3.10'
Requires-Dist: coverage ; extra == "tests"
Requires-Dist: pytest ; extra == "tests"
Requires-Dist: pytest-cov ; extra == "tests"
Requires-Dist: pytest-timeout ; extra == "tests"
Project-URL: Homepage, https://github.com/chrisjsewell/process-plot
Provides-Extra: tests
